stepng/__init__.py
stepng/__main__.py
stepng-1.0.3.dist-info/LICENSE
stepng-1.0.3.dist-info/METADATA
stepng-1.0.3.dist-info/WHEEL
stepng-1.0.3.dist-info/entry_points.txt
stepng-1.0.3.dist-info/top_level.txt
stepng-1.0.3.dist-info/RECORD
