Metadata-Version: 2.1
Name: stepng
Version: 1.0.3
Summary: Encode data into photos
Home-page: https://github.com/donno2048/stepng
Author: Elisha Hollander
License: MIT
Platform: UNKNOWN
Classifier: Programming Language :: Python :: 3
License-File: LICENSE
Requires-Dist: opencv-python
